{
  "title": {
    "en": "Video Production",
    "sv": "Videoproduktion"
  },
  "description": {
    "en": "Craft visual stories with video production services, from concept to final cut. Elevate your brand with high-quality video content.",
    "sv": "Skapa visuella berättelser med videoproduktionstjänster, från koncept till färdig film. Stärk ditt varumärke med högkvalitativt videoinnehåll."
  },
  "icon": "PixelarticonsVideo",
  "category": {
    "en": "Media Services",
    "sv": "Mediatjänster"
  }
}
